pgeon-0.2.0a0.dist-info/LICENSE
pgeon-0.2.0a0.dist-info/WHEEL
pgeon-0.2.0a0.dist-info/RECORD
pgeon-0.2.0a0.dist-info/METADATA
pgeon-0.2.0a0.dist-info/top_level.txt
pgeon/_pgeon.cpython-311-x86_64-linux-gnu.so
pgeon/__init__.py
pgeon.libs/libgssapi_krb5-497db0c6.so.2.2
pgeon.libs/libcrypto-19957f5b.so.1.0.2k
pgeon.libs/libssl3-c220d197.so
pgeon.libs/liblber-2-7eefa761.4.so.2.10.7
pgeon.libs/libselinux-0922c95c.so.1
pgeon.libs/libplc4-4e123408.so
pgeon.libs/libkrb5support-d0bcff84.so.0.1
pgeon.libs/libplds4-f0f0f720.so
pgeon.libs/libpq-c4cf1c14.so.5.11
pgeon.libs/libkrb5-fcafa220.so.3.3
pgeon.libs/libnss3-c4407ea1.so
pgeon.libs/libk5crypto-b1f99d5c.so.3.1
pgeon.libs/libldap_r-2-f51b92e0.4.so.2.10.7
pgeon.libs/libpcre-9513aab5.so.1.2.0
pgeon.libs/libsasl2-84219a89.so.3.0.0
pgeon.libs/libkeyutils-dfe70bd6.so.1.5
pgeon.libs/libcom_err-2abe824b.so.2.1
pgeon.libs/libnssutil3-5292dbaa.so
pgeon.libs/libssl-2a9eae6f.so.1.0.2k
pgeon.libs/libnspr4-4f93563e.so
pgeon.libs/libsmime3-9d4a6fc6.so
pgeon.libs/libcrypt-17112bff.so.1
