Metadata-Version: 2.1
Name: pgeon
Version: 0.2.0a0
Summary: Apache Arrow PostgreSQL connector
License: MIT License
Project-URL: Homepage, https://github.com/0x0L/pgeon
Project-URL: Bug Tracker, https://github.com/0x0L/pgeon/issues
Keywords: arrow,postgresql
Classifier: License :: OSI Approved :: MIT License
Classifier: Programming Language :: Python :: 3
Classifier: Topic :: Database
Requires-Python: >=3.7
License-File: LICENSE
Requires-Dist: pyarrow
Provides-Extra: benchmarks
Requires-Dist: asyncpg ; extra == 'benchmarks'
Requires-Dist: psycopg[binary] ; extra == 'benchmarks'
Requires-Dist: pandas ; extra == 'benchmarks'
Requires-Dist: seaborn ; extra == 'benchmarks'
Provides-Extra: tests
Requires-Dist: pytest ; extra == 'tests'
